research_trends/__init__.py
research_trends/analyzer.py
research_trends/cli.py
research_trends/client.py
research_trends/config.py
research_trends/dashboard.py
research_trends/models.py
research_trends/py.typed
research_trends/recommender.py
research_trends/clients/__init__.py
research_trends/clients/crossref.py
research_trends/clients/google_scholar.py
research_trends/clients/openalex.py
research_trends/clients/pubmed.py
research_trends/clients/scopus.py
research_trends/clients/semantic_scholar.py
research_trends/clients/unified.py
research_trends_scopus-0.2.3.dist-info/licenses/LICENSE
research_trends_scopus-0.2.3.dist-info/METADATA
research_trends_scopus-0.2.3.dist-info/WHEEL
research_trends_scopus-0.2.3.dist-info/entry_points.txt
research_trends_scopus-0.2.3.dist-info/top_level.txt
research_trends_scopus-0.2.3.dist-info/RECORD
