Metadata-Version: 2.4
Name: research-trends-scopus
Version: 0.2.3
Summary: A comprehensive tool to retrieve research data from multiple academic databases (Scopus, OpenAlex, Semantic Scholar, CrossRef, PubMed, Google Scholar), analyze trends, and generate interactive dashboards with recommendations
Author-email: Research Trends Team <research-trends@example.com>
Maintainer-email: Research Trends Team <research-trends@example.com>
License: MIT
Project-URL: Homepage, https://github.com/research-trends/research-trends-scopus
Project-URL: Documentation, https://research-trends-scopus.readthedocs.io
Project-URL: Repository, https://github.com/research-trends/research-trends-scopus
Project-URL: Issues, https://github.com/research-trends/research-trends-scopus/issues
Project-URL: Changelog, https://github.com/research-trends/research-trends-scopus/blob/main/CHANGELOG.md
Keywords: scopus,openalex,semantic-scholar,crossref,pubmed,google-scholar,research,trends,analysis,dashboard,bibliometrics,scientometrics,academic,publications,citations,multi-source
Classifier: Development Status :: 4 - Beta
Classifier: Intended Audience :: Science/Research
Classifier: Intended Audience :: Developers
Classifier: License :: OSI Approved :: MIT License
Classifier: Operating System :: OS Independent
Classifier: Programming Language :: Python :: 3
Classifier: Programming Language :: Python :: 3.9
Classifier: Programming Language :: Python :: 3.10
Classifier: Programming Language :: Python :: 3.11
Classifier: Programming Language :: Python :: 3.12
Classifier: Topic :: Scientific/Engineering
Classifier: Topic :: Scientific/Engineering :: Information Analysis
Classifier: Topic :: Scientific/Engineering :: Visualization
Requires-Python: >=3.9
License-File: LICENSE
Requires-Dist: requests>=2.28.0
Requires-Dist: pandas>=1.5.0
Requires-Dist: numpy>=1.23.0
Requires-Dist: plotly>=5.10.0
Requires-Dist: dash>=2.7.0
Requires-Dist: dash-bootstrap-components>=1.3.0
Requires-Dist: scikit-learn>=1.1.0
Requires-Dist: networkx>=2.8.0
Requires-Dist: wordcloud>=1.8.0
Requires-Dist: python-dotenv>=0.21.0
Requires-Dist: pyyaml>=6.0
Requires-Dist: tqdm>=4.64.0
Requires-Dist: cachetools>=5.2.0
Provides-Extra: dev
Requires-Dist: pytest>=7.0.0; extra == "dev"
Requires-Dist: pytest-cov>=4.0.0; extra == "dev"
Requires-Dist: pytest-mock>=3.10.0; extra == "dev"
Requires-Dist: black>=22.0.0; extra == "dev"
Requires-Dist: isort>=5.10.0; extra == "dev"
Requires-Dist: flake8>=5.0.0; extra == "dev"
Requires-Dist: mypy>=0.990; extra == "dev"
Requires-Dist: pre-commit>=2.20.0; extra == "dev"
Provides-Extra: docs
Requires-Dist: sphinx>=5.0.0; extra == "docs"
Requires-Dist: sphinx-rtd-theme>=1.0.0; extra == "docs"
Requires-Dist: sphinx-autodoc-typehints>=1.19.0; extra == "docs"
Requires-Dist: myst-parser>=0.18.0; extra == "docs"
Provides-Extra: notebook
Requires-Dist: jupyter>=1.0.0; extra == "notebook"
Requires-Dist: jupyterlab>=3.5.0; extra == "notebook"
Requires-Dist: ipywidgets>=8.0.0; extra == "notebook"
Requires-Dist: nbformat>=5.7.0; extra == "notebook"
Provides-Extra: all
Requires-Dist: research-trends-scopus[dev,docs,notebook]; extra == "all"
Dynamic: license-file
